binggo.py
binggo-1.0.4.dist-info/METADATA
binggo-1.0.4.dist-info/WHEEL
binggo-1.0.4.dist-info/entry_points.txt
binggo-1.0.4.dist-info/top_level.txt
binggo-1.0.4.dist-info/RECORD
