Metadata-Version: 2.1
Name: binggo
Version: 1.0.4
Summary: The Bing Searcher On Python|Python Bing搜索工具
Home-page: UNKNOWN
Author: Python学霸
Author-email: python@xueba.com
License: UNKNOWN
Platform: UNKNOWN
Requires-Dist: mechanicalsoup
